LICENSE
MANIFEST.in
README.rst
setup.cfg
setup.py
versioneer.py
tests/__init__.py
tests/test_general.py
tpDcc/__init__.py
tpDcc/tools/__init__.py
tpDcc/tools/unittests/__init__.py
tpDcc/tools/unittests/__logging__.ini
tpDcc/tools/unittests/__version__.py
tpDcc/tools/unittests/_version.py
tpDcc/tools/unittests/core/__init__.py
tpDcc/tools/unittests/core/client.py
tpDcc/tools/unittests/core/consts.py
tpDcc/tools/unittests/core/controller.py
tpDcc/tools/unittests/core/model.py
tpDcc/tools/unittests/core/tool.py
tpDcc/tools/unittests/core/toolset.py
tpDcc/tools/unittests/core/view.py
tpDcc/tools/unittests/dccs/__init__.py
tpDcc/tools/unittests/dccs/maya/__init__.py
tpDcc/tools/unittests/dccs/maya/server.py
tpDcc/tools/unittests/widgets/__init__.py
tpDcc/tools/unittests/widgets/console.py
tpDcc/tools/unittests/widgets/tree.py
tpDcc_tools_unittests.egg-info/PKG-INFO
tpDcc_tools_unittests.egg-info/SOURCES.txt
tpDcc_tools_unittests.egg-info/dependency_links.txt
tpDcc_tools_unittests.egg-info/not-zip-safe
tpDcc_tools_unittests.egg-info/requires.txt
tpDcc_tools_unittests.egg-info/top_level.txt