Metadata-Version: 2.1
Name: tpDcc-tools-unittests
Version: 0.0.1
Summary: Tool to execute unit tests inside DCCs.
Home-page: https://github.com/tpDcc/tpDcc-tools-unittests
Author: Tomas Poveda
Author-email: tpovedatd@gmail.com
License: MIT
Platform: UNKNOWN
Provides-Extra: dev
Provides-Extra: test
